mrnaid/__init__.py
mrnaid/__version__.py
mrnaid/backend/.dockerignore
mrnaid/backend/Dockerfile
mrnaid/backend/__init__.py
mrnaid/backend/common/Evaluation.py
mrnaid/backend/common/OptimizationProblems.py
mrnaid/backend/common/OptimizationTask.py
mrnaid/backend/common/__init__.py
mrnaid/backend/common/__pycache__/Evaluation.cpython-39.pyc
mrnaid/backend/common/__pycache__/OptimizationProblems.cpython-39.pyc
mrnaid/backend/common/__pycache__/OptimizationTask.cpython-39.pyc
mrnaid/backend/common/__pycache__/__init__.cpython-39.pyc
mrnaid/backend/common/constraints/Constraints.py
mrnaid/backend/common/constraints/UridineDepletion.py
mrnaid/backend/common/constraints/__init__.py
mrnaid/backend/common/constraints/__pycache__/Constraints.cpython-39.pyc
mrnaid/backend/common/constraints/__pycache__/UridineDepletion.cpython-39.pyc
mrnaid/backend/common/objectives/Codon_pair_usage.py
mrnaid/backend/common/objectives/Dinucleotide_usage.py
mrnaid/backend/common/objectives/MFE.py
mrnaid/backend/common/objectives/MFE_optimization.py
mrnaid/backend/common/objectives/Objectives.py
mrnaid/backend/common/objectives/__init__.py
mrnaid/backend/common/objectives/.ipynb_checkpoints/Objectives-checkpoint.py
mrnaid/backend/common/objectives/__pycache__/Codon_pair_usage.cpython-39.pyc
mrnaid/backend/common/objectives/__pycache__/Dinucleotide_usage.cpython-39.pyc
mrnaid/backend/common/objectives/__pycache__/MFE.cpython-39.pyc
mrnaid/backend/common/objectives/__pycache__/MFE_optimization.cpython-39.pyc
mrnaid/backend/common/objectives/__pycache__/Objectives.cpython-39.pyc
mrnaid/backend/common/objectives/__pycache__/__init__.cpython-39.pyc
mrnaid/backend/common/objectives/data/codon_pair_usage_h_sapiens.json
mrnaid/backend/common/objectives/data/codon_pair_usage_m_musculus.json
mrnaid/backend/common/objectives/data/dinucleotides_usage_h_sapiens.json
mrnaid/backend/common/objectives/data/dinucleotides_usage_m_musculus.json
mrnaid/backend/common/utils/Datatypes.py
mRNAid-1.0.0.dist-info/LICENSE
mRNAid-1.0.0.dist-info/LICENSES_THIRD_PARTY
mRNAid-1.0.0.dist-info/METADATA
mRNAid-1.0.0.dist-info/WHEEL
mRNAid-1.0.0.dist-info/entry_points.txt
mRNAid-1.0.0.dist-info/top_level.txt
mRNAid-1.0.0.dist-info/RECORD
