Metadata-Version: 2.1
Name: mRNAid
Version: 1.0.0
Summary: mRNAid: experimentally validated open-source tool for optimization and visualisation of mRNA molecules
Home-page: https://github.com/Merck/mRNAid
Author: Nikita Vostrosablin
License: MIT
Keywords: mrna,mrnaid,optimization
Classifier: Programming Language :: Python :: 3
Requires-Python: >=3.8
License-File: LICENSE
License-File: LICENSES_THIRD_PARTY
Requires-Dist: viennarna
Requires-Dist: dnachisel
Requires-Dist: redis
Requires-Dist: celery
Requires-Dist: Biopython (<1.82)
Requires-Dist: proglog
Requires-Dist: docopt
Requires-Dist: flametree
Requires-Dist: python-codon-tables
Requires-Dist: pydantic
Requires-Dist: numpy (<2)
Requires-Dist: scipy
Requires-Dist: loguru
Requires-Dist: click
